MANIFEST.in
README.rst
setup.py
test.py
docs/CREDITS.txt
docs/HISTORY.rst
docs/LICENSE.txt
src/roughrider/__init__.py
src/roughrider.predicate/README.txt
src/roughrider.predicate/requirements.txt
src/roughrider.predicate/setup.py
src/roughrider.predicate/docs/CREDITS.txt
src/roughrider.predicate/docs/HISTORY.txt
src/roughrider.predicate/docs/LICENSE.txt
src/roughrider.predicate/src/roughrider/__init__.py
src/roughrider.predicate/src/roughrider.predicate.egg-info/SOURCES.txt
src/roughrider.predicate/src/roughrider.predicate.egg-info/dependency_links.txt
src/roughrider.predicate/src/roughrider.predicate.egg-info/namespace_packages.txt
src/roughrider.predicate/src/roughrider.predicate.egg-info/requires.txt
src/roughrider.predicate/src/roughrider.predicate.egg-info/top_level.txt
src/roughrider.predicate/src/roughrider/predicate/__init__.py
src/roughrider.predicate/src/roughrider/predicate/decorator.py
src/roughrider.predicate/src/roughrider/predicate/errors.py
src/roughrider.predicate/src/roughrider/predicate/validators.py
src/roughrider.predicate/tests/test_errors.py
src/roughrider.predicate/tests/test_http_errors.py
src/roughrider.predicate/tests/test_validators.py
src/roughrider.workflow.egg-info/PKG-INFO
src/roughrider.workflow.egg-info/SOURCES.txt
src/roughrider.workflow.egg-info/dependency_links.txt
src/roughrider.workflow.egg-info/namespace_packages.txt
src/roughrider.workflow.egg-info/not-zip-safe
src/roughrider.workflow.egg-info/requires.txt
src/roughrider.workflow.egg-info/top_level.txt
src/roughrider/workflow/__init__.py
src/roughrider/workflow/components.py
src/roughrider/workflow/workflow.py
tests/test_action.py
tests/test_state.py
tests/test_transition.py
tests/test_workflow.py