Metadata-Version: 2.1
Name: roughrider.workflow
Version: 0.2
Summary: Pure python workflow/transition system.
Home-page: https://github.com/HorsemanWSGI/roughrider.workflow
Author: Souheil CHELFOUH
Author-email: trollfot@gmail.com
License: ZPL
Download-URL: http://pypi.python.org/pypi/roughrider.workflow
Platform: UNKNOWN
Classifier: Environment :: Web Environment
Classifier: Intended Audience :: Developers
Classifier: License :: OSI Approved :: Zope Public License
Classifier: Programming Language :: Python :: 3.8
Classifier: Programming Language :: Python :: 3.9
Classifier: Programming Language :: Python :: 3.10
Provides-Extra: test
